{
  "Common": {
    "thanks": "Gracias"
  },
  "HomePage": {},
  "ErrorPage": {
    "title": "Algo salió mal",
    "cta-button": "Volver al inicio"
  },
  "NotFound": {
    "title": "¡Vaya!",
    "description": "La página que buscas no existe.",
    "cta-button": "Volver al inicio"
  },
  "Metadata": {
    "title": "Rick and Morty Challenge - Ezequiel Grigolatto",
    "description": "Rick and Morty Challenge desarrollado por Ezequiel Grigolatto para Conexa",
    "keywords": "Rick and Morty, Conexa, Ezequiel Grigolatto, Frontend Developer, Challenge, Next.js, React, TypeScript"
  }
}